CHANGES.txt
INSTALL.txt
LICENSE.ZPL
README.txt
SPONSORS.txt
buildout-zeo.cfg
buildout.cfg
setup.py
versions.cfg
bootstrap/bootstrap.py
scripts/oooctl.py
scripts/prepare.py
scripts/setup.py
src/psj/__init__.py
src/psj.site.egg-info/PKG-INFO
src/psj.site.egg-info/SOURCES.txt
src/psj.site.egg-info/dependency_links.txt
src/psj.site.egg-info/entry_points.txt
src/psj.site.egg-info/namespace_packages.txt
src/psj.site.egg-info/not-zip-safe
src/psj.site.egg-info/requires.txt
src/psj.site.egg-info/top_level.txt
src/psj/site/README.txt
src/psj/site/__init__.py
src/psj/site/configure.zcml
src/psj/site/Extensions/Install.py
src/psj/site/Extensions/__init__.py
src/psj/site/profiles/default/types.xml
src/psj/site/profiles/default/types/PSJ_Document.xml
src/psj/site/tests/__init__.py
src/psj/site/tests/alientext.odt
src/psj/site/tests/simpledoc.doc
src/psj/site/tests/simpledoc.odt
src/psj/site/tests/test_setup.py