Metadata-Version: 1.0
Name: psj.site
Version: 0.1
Summary: Plone Scholarly Journal - the site setup
Home-page: http://pypi.python.org/pypi/psj.site
Author: Uli Fouquet
Author-email: uli@gnufix.de
License: GPL
Keywords: zope site scholarly scholar journal plone plone3
Platform: UNKNOWN
Classifier: Development Status :: 3 - Alpha
Classifier: Environment :: Web Environment
Classifier: Intended Audience :: Developers
Classifier: License :: OSI Approved :: Zope Public License
Classifier: Programming Language :: Python
Classifier: Operating System :: OS Independent
Classifier: Framework :: Zope2
